dnp3protocol/__init__.py
dnp3protocol/dnp3api.py
dnp3protocol/dnp3types.py
dnp3protocol/dnp3x64d.dll
dnp3protocol/iec60870common.py
dnp3protocol/libx86_x64-dnp3.so
dnp3protocol/structureWithEnums.py
dnp3protocol/tgtcommon.py
dnp3protocol/tgtdefines.py
dnp3protocol/tgterrorcodes.py
dnp3protocol/tgterrorvalues.py
dnp3protocol/tgtserialtypes.py
dnp3protocol/tgttypes.py
dnp3protocol/tests/dnp3clienttest.py
dnp3protocol/tests/dnp3servertest.py
dnp3protocol-21.6.19.dist-info/licenses/LICENSE
dnp3protocol-21.6.19.dist-info/METADATA
dnp3protocol-21.6.19.dist-info/WHEEL
dnp3protocol-21.6.19.dist-info/top_level.txt
dnp3protocol-21.6.19.dist-info/RECORD
