Metadata-Version: 2.4
Name: dnp3protocol
Version: 21.6.19
Summary: Distributed Network Protocol 3 (DNP3) protocol Server and Client Implementation - Python Wrapper 
Home-page: https://www.freyrscada.com/dnp3-python.php
Author: FreyrSCADA
Author-email: contact@freyrscada.com
Classifier: Programming Language :: Python :: 3
Classifier: License :: OSI Approved :: MIT License
Classifier: Operating System :: Microsoft :: Windows
Classifier: Operating System :: POSIX :: Linux
License-File: LICENSE
Dynamic: author
Dynamic: author-email
Dynamic: classifier
Dynamic: description
Dynamic: description-content-type
Dynamic: home-page
Dynamic: license-file
Dynamic: summary
